psic/__init__.py
psic/calc_fraction.py
psic/create_mesh.py
psic/create_submodel.py
psic/packing_spheres_in_cube.py
psic/plot_model.py
psic/wrappers.py
psic-0.1.2.dist-info/LICENSE
psic-0.1.2.dist-info/METADATA
psic-0.1.2.dist-info/WHEEL
psic-0.1.2.dist-info/top_level.txt
psic-0.1.2.dist-info/RECORD
