Metadata-Version: 2.1
Name: psic
Version: 0.1.2
Summary: Packing Spheres In Cube
Home-page: https://github.com/sunwhale/psic
Author: Jingyu Sun
Author-email: sun.jingyu@outlook.com
Project-URL: Bug Tracker, https://github.com/sunwhale/psic/issues
Classifier: Programming Language :: Python :: 3
Classifier: License :: OSI Approved :: Apache Software License
Classifier: Operating System :: OS Independent
Requires-Python: >=3.9
License-File: LICENSE
Requires-Dist: numpy
Requires-Dist: scipy
Requires-Dist: matplotlib
